datawave_haproxy_agent/__init__.py
datawave_haproxy_agent/__main__.py
datawave_haproxy_agent/agent.py
datawave_haproxy_agent/dwserverhealth.py
datawave_haproxy_agent-1.0.0.dist-info/LICENSE
datawave_haproxy_agent-1.0.0.dist-info/METADATA
datawave_haproxy_agent-1.0.0.dist-info/WHEEL
datawave_haproxy_agent-1.0.0.dist-info/entry_points.txt
datawave_haproxy_agent-1.0.0.dist-info/top_level.txt
datawave_haproxy_agent-1.0.0.dist-info/RECORD
