Metadata-Version: 2.1
Name: datawave-haproxy-agent
Version: 1.0.0
Summary: Datawave HAProxy Agent
Home-page: https://github.com/brianloss/datawave-haproxy-agent
Author: Brian Loss
Author-email: brianloss@gmail.com
License: UNKNOWN
Keywords: datawave haproxy agent load-balancer
Platform: UNKNOWN
Classifier: Development Status :: 5 - Production/Stable
Classifier: Intended Audience :: Developers
Classifier: Intended Audience :: System Administrators
Classifier: Topic :: Internet :: WWW/HTTP :: HTTP Servers
Classifier: License :: OSI Approved :: Apache Software License
Classifier: Programming Language :: Python :: 2
Classifier: Programming Language :: Python :: 2.7
Classifier: Programming Language :: Python :: 3
Classifier: Programming Language :: Python :: 3.4
Classifier: Programming Language :: Python :: 3.5
Classifier: Programming Language :: Python :: 3.6
Classifier: Programming Language :: Python :: 3.8
Classifier: Programming Language :: Python :: 3.9
Requires-Dist: gevent
Requires-Dist: urllib3
Requires-Dist: PyYAML
